{"stat.mineBlock.14":13,"stat.mineBlock.13":262,"stat.flyOneCm":22509,"stat.mineBlock.16":374,"stat.killEntity.Skeleton":1,"stat.deaths":1,"stat.mineBlock.15":278,"stat.walkOneCm":20747,"stat.drop":10,"stat.jump":28,"stat.playOneMinute":7851,"achievement.openInventory":12,"stat.damageTaken":-2147479439,"stat.killEntity.Spider":1,"stat.damageDealt":15129840,"stat.mineBlock.3":992,"stat.killEntity.Zombie":2,"stat.mineBlock.1":35954,"stat.mobKills":4,"stat.mineBlock.73":21,"achievement.exploreAllBiomes":{"value":0,"progress":["FrozenRiver","Ice Plains","Taiga","Ice Mountains"]},"stat.mineBlock.78":1}