{"stat.useItem.153":2,"stat.mineBlock.13":106,"stat.flyOneCm":782,"stat.mineBlock.16":12,"stat.useItem.56":2,"stat.mineBlock.15":15,"stat.walkOneCm":5405,"stat.drop":16,"stat.useItem.145":1,"stat.jump":3,"stat.useItem.73":1,"stat.playOneMinute":3850,"achievement.openInventory":19,"stat.useItem.116":1,"stat.useItem.129":3,"stat.damageTaken":10,"stat.mineBlock.3":150,"stat.mineBlock.153":1,"stat.mineBlock.1":7471,"stat.mineBlock.129":2,"stat.mineBlock.73":1,"achievement.exploreAllBiomes":{"value":0,"progress":["Taiga"]},"stat.mineBlock.56":1}